matplotlib_window/__init__.py
matplotlib_window/base.py
matplotlib_window/window.py
matplotlib_window-1.1.0.dist-info/METADATA
matplotlib_window-1.1.0.dist-info/WHEEL
matplotlib_window-1.1.0.dist-info/licenses/LICENSE
matplotlib_window-1.1.0.dist-info/RECORD
