Metadata-Version: 2.4
Name: matplotlib-window
Version: 1.1.0
Summary: Draggable data windowing for matplotlib plots
Project-URL: Homepage, https://github.com/sco1/
Project-URL: Documentation, https://github.com/sco1/matplotlib-window/blob/main/README.md
Project-URL: Repository, https://github.com/sco1/matplotlib-window
Project-URL: Issues, https://github.com/sco1/matplotlib-window/issues
Project-URL: Changelog, https://github.com/sco1/matplotlib-window/blob/main/CHANGELOG.md
Author-email: sco1 <sco1.git@gmail.com>
Maintainer-email: sco1 <sco1.git@gmail.com>
License-File: LICENSE
Classifier: Development Status :: 4 - Beta
Classifier: Intended Audience :: Developers
Classifier: License :: OSI Approved :: MIT License
Classifier: Operating System :: OS Independent
Classifier: Programming Language :: Python :: 3 :: Only
Classifier: Programming Language :: Python :: 3.11
Classifier: Programming Language :: Python :: 3.12
Classifier: Programming Language :: Python :: 3.13
Classifier: Typing :: Typed
Requires-Python: >=3.11
Requires-Dist: matplotlib~=3.9
